[{"timestamp":"2024-12-01T01:12:31.673Z","count":0,"uniques":0},{"timestamp":"2025-01-01T01:04:33.500Z","count":0,"uniques":0},{"timestamp":"2025-02-01T01:07:09.824Z","count":0,"uniques":0},{"timestamp":"2025-03-01T01:11:05.923Z","count":0,"uniques":0},{"timestamp":"2025-04-01T01:11:19.151Z","count":0,"uniques":0},{"timestamp":"2025-05-01T01:14:14.139Z","count":0,"uniques":0},{"timestamp":"2025-06-01T01:19:18.919Z","count":0,"uniques":0},{"timestamp":"2025-07-01T01:18:07.259Z","count":0,"uniques":0},{"timestamp":"2025-08-01T01:20:08.818Z","count":0,"uniques":0},{"timestamp":"2025-09-01T01:12:18.445Z","count":0,"uniques":0},{"timestamp":"2025-10-01T01:08:42.368Z","count":0,"uniques":0},{"timestamp":"2025-11-01T01:18:42.272Z","count":0,"uniques":0},{"timestamp":"2025-12-01T01:17:54.816Z","count":1,"uniques":1}]
