[{"timestamp":"2024-12-01T01:14:42.401Z","count":7,"uniques":2},{"timestamp":"2025-01-01T01:10:17.366Z","count":0,"uniques":0},{"timestamp":"2025-02-01T01:13:06.434Z","count":0,"uniques":0},{"timestamp":"2025-03-01T01:16:59.129Z","count":0,"uniques":0},{"timestamp":"2025-04-01T01:17:28.717Z","count":0,"uniques":0},{"timestamp":"2025-05-01T01:19:40.689Z","count":1,"uniques":1},{"timestamp":"2025-06-01T01:25:40.380Z","count":0,"uniques":0},{"timestamp":"2025-07-01T01:24:06.705Z","count":0,"uniques":0},{"timestamp":"2025-08-01T01:30:12.809Z","count":1,"uniques":1},{"timestamp":"2025-09-01T01:18:25.578Z","count":0,"uniques":0},{"timestamp":"2025-10-01T01:22:46.398Z","count":1,"uniques":1},{"timestamp":"2025-11-01T01:24:34.129Z","count":0,"uniques":0},{"timestamp":"2025-12-01T01:22:55.900Z","count":0,"uniques":0}]
