[{"timestamp":"2022-05-01T01:10:05.009Z","count":47,"uniques":7},{"timestamp":"2022-06-01T01:12:20.290Z","count":8,"uniques":3},{"timestamp":"2022-07-01T01:16:08.851Z","count":6,"uniques":2},{"timestamp":"2022-08-01T01:25:34.107Z","count":0,"uniques":0},{"timestamp":"2022-09-01T01:24:22.194Z","count":0,"uniques":0},{"timestamp":"2022-10-01T01:43:17.610Z","count":0,"uniques":0},{"timestamp":"2022-11-01T01:15:37.078Z","count":3,"uniques":1},{"timestamp":"2022-12-01T01:10:56.324Z","count":57,"uniques":4},{"timestamp":"2023-01-01T01:05:45.865Z","count":39,"uniques":4},{"timestamp":"2023-02-01T01:04:41.630Z","count":0,"uniques":0},{"timestamp":"2023-03-01T01:12:20.732Z","count":0,"uniques":0},{"timestamp":"2023-04-01T01:04:10.431Z","count":129,"uniques":6}]
